README.md
setup.py
fleetgo/__init__.py
fleetgo/address.py
fleetgo/api.py
fleetgo/authentication.py
fleetgo/device.py
fleetgo/json_utils.py
fleetgo/trip.py
fleetgo/tripdetail.py
fleetgo.egg-info/PKG-INFO
fleetgo.egg-info/SOURCES.txt
fleetgo.egg-info/dependency_links.txt
fleetgo.egg-info/not-zip-safe
fleetgo.egg-info/requires.txt
fleetgo.egg-info/top_level.txt