Metadata-Version: 1.2
Name: fleetgo
Version: 0.9.6
Summary: FleetGO API Access
Home-page: http://github.com/depl0y/fleetgo-py
Author: Wim Haanstra
Author-email: wim@wim.me
License: MIT
Platform: UNKNOWN
Requires-Python: >=3
